django_popup_view_field/__init__.py
django_popup_view_field/apps.py
django_popup_view_field/exceptions.py
django_popup_view_field/fields.py
django_popup_view_field/registry.py
django_popup_view_field/tests.py
django_popup_view_field/urls.py
django_popup_view_field/views.py
django_popup_view_field/widgets.py
django_popup_view_field/locale/pl/LC_MESSAGES/django.mo
django_popup_view_field/locale/pl/LC_MESSAGES/django.po
django_popup_view_field/locale/pl/LC_MESSAGES/djangojs.mo
django_popup_view_field/locale/pl/LC_MESSAGES/djangojs.po
django_popup_view_field/migrations/__init__.py
django_popup_view_field/static/django_popup_view_field/js/django_popup_view_field_bootstrap3.js
django_popup_view_field/static/django_popup_view_field/js/django_popup_view_field_bootstrap3.min.js
django_popup_view_field/static/django_popup_view_field/js/django_popup_view_field_bootstrap4.js
django_popup_view_field/static/django_popup_view_field/js/django_popup_view_field_bootstrap4.min.js
django_popup_view_field/templates/django_popup_view_field/popup_view_dialog_bootstrap3.html
django_popup_view_field/templates/django_popup_view_field/popup_view_dialog_bootstrap4.html
django_popup_view_field/templates/django_popup_view_field/popup_view_widget_bootstrap3.html
django_popup_view_field/templates/django_popup_view_field/popup_view_widget_bootstrap4.html
django_popup_view_field/templates/django_popup_view_field/scripts_include.html
django_popup_view_field/templatetags/__init__.py
django_popup_view_field/templatetags/django_popup_view_field_tags.py
django_popup_view_field/tests/__init__.py
django_popup_view_field/tests/forms.py
django_popup_view_field/tests/popups.py
django_popup_view_field/tests/settings.py
django_popup_view_field/tests/test_field.py
django_popup_view_field/tests/test_registry.py
django_popup_view_field/tests/test_templatetags.py
django_popup_view_field/tests/test_views.py
django_popup_view_field/tests/test_widgets.py
django_popup_view_field/tests/urls.py
django_popup_view_field-0.6.1.dist-info/LICENSE
django_popup_view_field-0.6.1.dist-info/METADATA
django_popup_view_field-0.6.1.dist-info/WHEEL
django_popup_view_field-0.6.1.dist-info/top_level.txt
django_popup_view_field-0.6.1.dist-info/RECORD
