Metadata-Version: 2.1
Name: django-popup-view-field
Version: 0.6.1
Summary: Field and widget can render bootstrap dialog window with content from django view
Home-page: https://github.com/djk2/django-popup-view-field
Author: Grzegorz Tężycki
Author-email: grzegorz.tezycki@gmail.com
License: MIT
Keywords: popup crispy bootstrap views
Platform: UNKNOWN
Classifier: Environment :: Web Environment
Classifier: Framework :: Django
Classifier: License :: OSI Approved :: MIT License
Classifier: Operating System :: OS Independent
Classifier: Programming Language :: Python
Classifier: Programming Language :: Python :: 2
Classifier: Programming Language :: Python :: 2.7
Classifier: Programming Language :: Python :: 3
Classifier: Programming Language :: Python :: 3.6
Classifier: Topic :: Utilities
Requires-Dist: Django (>=1.8)
